tpaw/__init__.py
tpaw-0.0.1a4.dist-info/LICENSE
tpaw-0.0.1a4.dist-info/WHEEL
tpaw-0.0.1a4.dist-info/METADATA
tpaw-0.0.1a4.dist-info/RECORD
